pyJuniper/__init__.py
pyJuniper/hierarchy.py
pyJuniper/hierarchy_rules.py
pyJuniper/jset.py
pyJuniper/juniper.py
pyJuniper-0.0.2.dist-info/LICENSE
pyJuniper-0.0.2.dist-info/METADATA
pyJuniper-0.0.2.dist-info/WHEEL
pyJuniper-0.0.2.dist-info/top_level.txt
pyJuniper-0.0.2.dist-info/RECORD
