Metadata-Version: 2.1
Name: pyJuniper
Version: 0.0.2
Summary: Networking Device MD5 Password Encrypt/Decrypt utility
Home-page: https://github.com/aliasgar1978/pyJuniper
Author: ALIASGAR - ALI
Author-email: aholo2000@gmail.com
Classifier: Programming Language :: Python :: 3
Classifier: License :: OSI Approved :: MIT License
Classifier: Operating System :: OS Independent
Requires-Python: >=3.8
License-File: LICENSE
Requires-Dist: nettoolkit-common
